extensible_splines/__init__.py
extensible_splines/splines.py
extensible_splines-0.2.1.dist-info/LICENSE
extensible_splines-0.2.1.dist-info/METADATA
extensible_splines-0.2.1.dist-info/WHEEL
extensible_splines-0.2.1.dist-info/top_level.txt
extensible_splines-0.2.1.dist-info/RECORD
