Metadata-Version: 2.1
Name: extensible_splines
Version: 0.2.1
Summary: Simple, easily verified custom spline interpolation.
Home-page: https://github.com/egoughnour/extensible-splines
Author: E Goughnour
Author-email: e.goughnour@gmail.com
License: MIT
Classifier: Programming Language :: Python :: 3.8
Classifier: Programming Language :: Python :: 3.9
Classifier: Programming Language :: Python :: 3.10
Classifier: Programming Language :: Python :: 3.11
License-File: LICENSE
Requires-Dist: matplotlib
